MANIFEST.in
README.rst
setup.py
cmsplugin_socialbuttons/__init__.py
cmsplugin_socialbuttons/cms_plugins.py
cmsplugin_socialbuttons/models.py
cmsplugin_socialbuttons.egg-info/PKG-INFO
cmsplugin_socialbuttons.egg-info/SOURCES.txt
cmsplugin_socialbuttons.egg-info/dependency_links.txt
cmsplugin_socialbuttons.egg-info/not-zip-safe
cmsplugin_socialbuttons.egg-info/top_level.txt
cmsplugin_socialbuttons/locale/de/LC_MESSAGES/django.mo
cmsplugin_socialbuttons/locale/de/LC_MESSAGES/django.po
cmsplugin_socialbuttons/migrations/0001_initial.py
cmsplugin_socialbuttons/migrations/__init__.py
cmsplugin_socialbuttons/static/cmsplugin_socialbuttons/css/cmsplugin_socialbuttons.css
cmsplugin_socialbuttons/static/cmsplugin_socialbuttons/img/buttons.png
cmsplugin_socialbuttons/static/cmsplugin_socialbuttons/js/cmsplugin_socialbuttons.js
cmsplugin_socialbuttons/templates/cmsplugin_socialbuttons/button.html
cmsplugin_socialbuttons/templates/cmsplugin_socialbuttons/list.html
cmsplugin_socialbuttons/templatetags/__init__.py
cmsplugin_socialbuttons/templatetags/cmsplugin_socialbuttons_tags.py