Metadata-Version: 1.0
Name: cmsplugin-socialbuttons
Version: 0.1.2
Summary: A simple plugin for adding social buttons.
Home-page: https://github.com/jurheinsieg/cmsplugin-socialbuttons
Author: Raphael Jasjukaitis
Author-email: webmaster@raphaa.de
License: UNKNOWN
Platform: UNKNOWN
Classifier: Environment :: Web Environment
Classifier: License :: OSI Approved :: BSD License
Classifier: Operating System :: OS Independent
Classifier: Programming Language :: Python
Classifier: Framework :: Django
